stripnet/__init__.py
stripnet/stripnet.py
stripnet/utils.py
stripnet-0.0.7.dist-info/LICENSE
stripnet-0.0.7.dist-info/METADATA
stripnet-0.0.7.dist-info/WHEEL
stripnet-0.0.7.dist-info/top_level.txt
stripnet-0.0.7.dist-info/RECORD
