Metadata-Version: 2.1
Name: stripnet
Version: 0.0.7
Summary: STriP Net: Semantic Similarity of Scientific Papers (S3P) Network
Home-page: https://github.com/stephenleo/stripnet
Author: stephenleo
Author-email: stephen.leo87@gmail.com
License: UNKNOWN
Platform: UNKNOWN
Classifier: Programming Language :: Python
Classifier: Programming Language :: Python :: 3
Classifier: Programming Language :: Python :: 3.6
Classifier: Programming Language :: Python :: 3.7
Classifier: Programming Language :: Python :: 3.8
Classifier: Operating System :: OS Independent
Requires-Python: >=3.6, <3.9
License-File: LICENSE
Requires-Dist: cython
Requires-Dist: numpy
Requires-Dist: bertopic
Requires-Dist: networkx
Requires-Dist: pandas
Requires-Dist: plotly
Requires-Dist: pyvis
Requires-Dist: scikit-learn
Requires-Dist: sentence-transformers
Requires-Dist: ipywidgets
